pipgeo/__init__.py
pipgeo/pipgeo.py
pipgeo-0.1.0.dist-info/licenses/LICENSE
pipgeo-0.1.0.dist-info/METADATA
pipgeo-0.1.0.dist-info/WHEEL
pipgeo-0.1.0.dist-info/entry_points.txt
pipgeo-0.1.0.dist-info/top_level.txt
pipgeo-0.1.0.dist-info/RECORD
