Metadata-Version: 2.4
Name: pipgeo
Version: 0.1.0
Summary: CLI for Unofficial Windows Geospatial library wheels
Author-email: Samapriya Roy <samapriya.roy@gmail.com>
Maintainer-email: Samapriya Roy <samapriya.roy@gmail.com>
License-Expression: Apache-2.0
Project-URL: Homepage, https://github.com/samapriya/pipgeo
Project-URL: Documentation, https://github.com/samapriya/pipgeo#readme
Project-URL: Repository, https://github.com/samapriya/pipgeo
Project-URL: Bug Reports, https://github.com/samapriya/pipgeo/issues
Project-URL: Changelog, https://github.com/samapriya/pipgeo/releases
Keywords: geospatial,gis,gdal,windows,wheels,cli
Classifier: Development Status :: 5 - Production/Stable
Classifier: Intended Audience :: Developers
Classifier: Intended Audience :: Science/Research
Classifier: Natural Language :: English
Classifier: Programming Language :: Python :: 3
Classifier: Programming Language :: Python :: 3.11
Classifier: Programming Language :: Python :: 3.12
Classifier: Programming Language :: Python :: 3.13
Classifier: Operating System :: Microsoft :: Windows
Classifier: Topic :: Scientific/Engineering :: GIS
Classifier: Topic :: Software Development :: Libraries :: Python Modules
Requires-Python: >=3.11
License-File: LICENSE
Requires-Dist: requests>=2.31.0
Requires-Dist: beautifulsoup4>=4.12.0
Requires-Dist: packaging>=23.0
Requires-Dist: uv>=0.1.0
Provides-Extra: dev
Requires-Dist: pytest>=7.0.0; extra == "dev"
Requires-Dist: black>=23.0.0; extra == "dev"
Requires-Dist: ruff>=0.1.0; extra == "dev"
Dynamic: license-file
